asyncrepo/__init__.py
asyncrepo/exceptions.py
asyncrepo/repository.py
asyncrepo-0.0.9.dist-info/LICENSE
asyncrepo-0.0.9.dist-info/METADATA
asyncrepo-0.0.9.dist-info/WHEEL
asyncrepo-0.0.9.dist-info/top_level.txt
asyncrepo-0.0.9.dist-info/RECORD
