Metadata-Version: 2.1
Name: asyncrepo
Version: 0.0.9
Summary: A library for providing a unified asyncio API for various data sources
Home-page: https://github.com/nottheswimmer/asyncrepo
Author: Michael Phelps
Author-email: michaelphelps@nottheswimmer.org
License: MIT
Classifier: Development Status :: 2 - Pre-Alpha
Classifier: Intended Audience :: Developers
Classifier: License :: OSI Approved :: MIT License
Classifier: Programming Language :: Python :: 3
Classifier: Programming Language :: Python :: 3.10
Classifier: Topic :: Software Development :: Libraries
Classifier: Topic :: Software Development :: Libraries :: Python Modules
License-File: LICENSE
Requires-Dist: aioboto3 (==9.6.0)
Requires-Dist: aiobotocore (==2.3.0)
Requires-Dist: aiocsv (==1.2.2)
Requires-Dist: aiofile (==3.7.4)
Requires-Dist: aiohttp (==3.8.1)
Requires-Dist: aioitertools (==0.10.0)
Requires-Dist: aiopath (==0.6.10)
Requires-Dist: aiosignal (==1.2.0)
Requires-Dist: anyio (==3.6.1)
Requires-Dist: async-timeout (==4.0.2)
Requires-Dist: atomicwrites (==1.4.1)
Requires-Dist: attrs (==21.4.0)
Requires-Dist: bleach (==5.0.1)
Requires-Dist: boto3 (==1.21.21)
Requires-Dist: botocore (==1.24.21)
Requires-Dist: build (==0.8.0)
Requires-Dist: caio (==0.9.6)
Requires-Dist: certifi (==2022.6.15)
Requires-Dist: cffi (==1.15.1)
Requires-Dist: charset-normalizer (==2.1.0)
Requires-Dist: colorama (==0.4.5)
Requires-Dist: commonmark (==0.9.1)
Requires-Dist: Deprecated (==1.2.13)
Requires-Dist: docutils (==0.19)
Requires-Dist: execnet (==1.9.0)
Requires-Dist: frozenlist (==1.3.0)
Requires-Dist: idna (==3.3)
Requires-Dist: importlib-metadata (==4.12.0)
Requires-Dist: iniconfig (==1.1.1)
Requires-Dist: jmespath (==1.0.1)
Requires-Dist: keyring (==23.6.0)
Requires-Dist: multidict (==6.0.2)
Requires-Dist: packaging (==21.3)
Requires-Dist: pep517 (==0.12.0)
Requires-Dist: pkginfo (==1.8.3)
Requires-Dist: pluggy (==1.0.0)
Requires-Dist: py (==1.11.0)
Requires-Dist: pycparser (==2.21)
Requires-Dist: PyGithub (==1.55)
Requires-Dist: Pygments (==2.12.0)
Requires-Dist: PyJWT (==2.4.0)
Requires-Dist: PyNaCl (==1.5.0)
Requires-Dist: pyparsing (==3.0.9)
Requires-Dist: pytest (==7.1.2)
Requires-Dist: pytest-asyncio (==0.18.3)
Requires-Dist: pytest-forked (==1.4.0)
Requires-Dist: pytest-rerunfailures (==10.2)
Requires-Dist: pytest-xdist (==2.5.0)
Requires-Dist: python-dateutil (==2.8.2)
Requires-Dist: python-dotenv (==0.20.0)
Requires-Dist: pywin32-ctypes (==0.2.0)
Requires-Dist: readme-renderer (==35.0)
Requires-Dist: requests (==2.28.1)
Requires-Dist: requests-toolbelt (==0.9.1)
Requires-Dist: rfc3986 (==2.0.0)
Requires-Dist: rich (==12.4.4)
Requires-Dist: s3transfer (==0.5.2)
Requires-Dist: six (==1.16.0)
Requires-Dist: sniffio (==1.2.0)
Requires-Dist: tomli (==2.0.1)
Requires-Dist: twine (==4.0.1)
Requires-Dist: urllib3 (==1.26.10)
Requires-Dist: webencodings (==0.5.1)
Requires-Dist: wrapt (==1.14.1)
Requires-Dist: yarl (==1.7.2)
Requires-Dist: zipp (==3.8.0)
